ffmpegx/__init__.py
ffmpegx/py.typed
ffmpegx/stream.py
ffmpegx-0.1.0.dist-info/METADATA
ffmpegx-0.1.0.dist-info/WHEEL
ffmpegx-0.1.0.dist-info/licenses/LICENSE
ffmpegx-0.1.0.dist-info/RECORD
