Metadata-Version: 2.4
Name: ffmpegx
Version: 0.1.0
Summary: A wrapper of ffmpeg
Author-email: levinion <levinnion@gmail.com>
License-File: LICENSE
Requires-Python: >=3.13
